<?xml version="1.0" encoding="utf-8" ?>
<dwsync>
<file name="application.twig" server="ec2-44-202-10-232.compute-1.amazonaws.com//var/www/html/" local="132947146946054264" remote="132947167090000000" Dst="2" />
<file name="application_configure.twig" server="ec2-44-202-10-232.compute-1.amazonaws.com//var/www/html/" local="132947146946237769" remote="132947167090000000" Dst="2" />
<file name="invalid.twig" server="ec2-44-202-10-232.compute-1.amazonaws.com//var/www/html/" local="132947146946421292" remote="132947167090000000" Dst="2" />
<file name="key-https-warning.twig" server="ec2-44-202-10-232.compute-1.amazonaws.com//var/www/html/" local="132947146946619703" remote="132947167080000000" Dst="2" />
<file name="key.twig" server="ec2-44-202-10-232.compute-1.amazonaws.com//var/www/html/" local="132947146946788338" remote="132947167080000000" Dst="2" />
<file name="key_configure.twig" server="ec2-44-202-10-232.compute-1.amazonaws.com//var/www/html/" local="132947146946966905" remote="132947167080000000" Dst="2" />
<file name="simple.twig" server="ec2-44-202-10-232.compute-1.amazonaws.com//var/www/html/" local="132947146947135542" remote="132947167080000000" Dst="2" />
<file name="application.twig" server="ec2-52-53-236-237.us-west-1.compute.amazonaws.com//var/www/html/" local="132890229580000000" remote="132943555140000000" Dst="2" />
<file name="application_configure.twig" server="ec2-52-53-236-237.us-west-1.compute.amazonaws.com//var/www/html/" local="132890229580000000" remote="132943555130000000" Dst="2" />
<file name="invalid.twig" server="ec2-52-53-236-237.us-west-1.compute.amazonaws.com//var/www/html/" local="132890229580000000" remote="132943555130000000" Dst="2" />
<file name="key-https-warning.twig" server="ec2-52-53-236-237.us-west-1.compute.amazonaws.com//var/www/html/" local="132890229580000000" remote="132943555130000000" Dst="2" />
<file name="key.twig" server="ec2-52-53-236-237.us-west-1.compute.amazonaws.com//var/www/html/" local="132890229580000000" remote="132943555130000000" Dst="2" />
<file name="key_configure.twig" server="ec2-52-53-236-237.us-west-1.compute.amazonaws.com//var/www/html/" local="132890229580000000" remote="132943555130000000" Dst="2" />
<file name="simple.twig" server="ec2-52-53-236-237.us-west-1.compute.amazonaws.com//var/www/html/" local="132890229580000000" remote="132943555120000000" Dst="2" />
</dwsync>